setup.py
yesno/__init__.py
yesno/weather.py
yesno.egg-info/PKG-INFO
yesno.egg-info/SOURCES.txt
yesno.egg-info/dependency_links.txt
yesno.egg-info/top_level.txt