Metadata-Version: 1.0
Name: yesno
Version: 0.1
Summary: Get answers to simple yes/no questions
Home-page: http://github.com/philippbosch/yesno
Author: Philipp Bosch
Author-email: hello@pb.io
License: MIT
Keywords: yes,no,question,answer
Platform: any
Classifier: Development Status :: 3 - Alpha
Classifier: Intended Audience :: Developers
Classifier: Natural Language :: English
Classifier: License :: OSI Approved :: MIT License
Classifier: Operating System :: OS Independent
Classifier: Programming Language :: Python
